symtensor/__init__.py
symtensor/version.py
symtensor-0.1.0.dist-info/METADATA
symtensor-0.1.0.dist-info/WHEEL
symtensor-0.1.0.dist-info/top_level.txt
symtensor-0.1.0.dist-info/RECORD
