Metadata-Version: 2.1
Name: symtensor
Version: 0.1.0
Summary: symtensor
Home-page: http://github.com/symtensor/symtensor/
Author: Zhiqing Xiao
Author-email: xzq.xiaozhiqing@gmail.com
Classifier: Programming Language :: Python
Classifier: Intended Audience :: Science/Research
